sixquant
tests
